AUTHORS.md
LICENSE
MANIFEST.in
README.md
requirements-dev.txt
requirements.txt
setup.cfg
setup.py
tox.ini
moto/__init__.py
moto/backend_index.py
moto/backends.py
moto/server.py
moto/settings.py
moto/acm/__init__.py
moto/acm/models.py
moto/acm/responses.py
moto/acm/urls.py
moto/acm/utils.py
moto/apigateway/__init__.py
moto/apigateway/exceptions.py
moto/apigateway/models.py
moto/apigateway/responses.py
moto/apigateway/urls.py
moto/apigateway/utils.py
moto/applicationautoscaling/__init__.py
moto/applicationautoscaling/exceptions.py
moto/applicationautoscaling/models.py
moto/applicationautoscaling/responses.py
moto/applicationautoscaling/urls.py
moto/applicationautoscaling/utils.py
moto/athena/__init__.py
moto/athena/exceptions.py
moto/athena/models.py
moto/athena/responses.py
moto/athena/urls.py
moto/athena/utils.py
moto/autoscaling/__init__.py
moto/autoscaling/exceptions.py
moto/autoscaling/models.py
moto/autoscaling/responses.py
moto/autoscaling/urls.py
moto/awslambda/__init__.py
moto/awslambda/exceptions.py
moto/awslambda/models.py
moto/awslambda/policy.py
moto/awslambda/responses.py
moto/awslambda/urls.py
moto/awslambda/utils.py
moto/batch/__init__.py
moto/batch/exceptions.py
moto/batch/models.py
moto/batch/responses.py
moto/batch/urls.py
moto/batch/utils.py
moto/cloudformation/__init__.py
moto/cloudformation/custom_model.py
moto/cloudformation/exceptions.py
moto/cloudformation/models.py
moto/cloudformation/parsing.py
moto/cloudformation/responses.py
moto/cloudformation/urls.py
moto/cloudformation/utils.py
moto/cloudtrail/__init__.py
moto/cloudtrail/exceptions.py
moto/cloudtrail/models.py
moto/cloudtrail/responses.py
moto/cloudtrail/urls.py
moto/cloudwatch/__init__.py
moto/cloudwatch/exceptions.py
moto/cloudwatch/models.py
moto/cloudwatch/responses.py
moto/cloudwatch/urls.py
moto/cloudwatch/utils.py
moto/codecommit/__init__.py
moto/codecommit/exceptions.py
moto/codecommit/models.py
moto/codecommit/responses.py
moto/codecommit/urls.py
moto/codepipeline/__init__.py
moto_ext_s3kmspatch.egg-info/PKG-INFO
moto_ext_s3kmspatch.egg-info/SOURCES.txt
moto_ext_s3kmspatch.egg-info/dependency_links.txt
moto_ext_s3kmspatch.egg-info/entry_points.txt
moto_ext_s3kmspatch.egg-info/requires.txt
moto_ext_s3kmspatch.egg-info/top_level.txt
