Metadata-Version: 2.1
Name: moto-ext-s3kmspatch
Version: 2.2.16.dev0
Summary: A library that allows your python tests to easily mock out the boto library
Home-page: https://github.com/spulec/moto
Author: Steve Pulec
Author-email: spulec@gmail.com
License: Apache
Project-URL: Documentation, http://docs.getmoto.org/en/latest/
Platform: UNKNOWN
Classifier: Programming Language :: Python :: 3
Classifier: Programming Language :: Python :: 3.5
Classifier: Programming Language :: Python :: 3.6
Classifier: Programming Language :: Python :: 3.7
Classifier: Programming Language :: Python :: 3.8
Classifier: Programming Language :: Python :: 3.9
Classifier: License :: OSI Approved :: Apache Software License
Classifier: Topic :: Software Development :: Testing
Provides-Extra: all
Provides-Extra: server
Provides-Extra: acm
Provides-Extra: apigateway
Provides-Extra: apigateway_deprecated
Provides-Extra: applicationautoscaling
Provides-Extra: athena
Provides-Extra: autoscaling
Provides-Extra: autoscaling_deprecated
Provides-Extra: batch
Provides-Extra: cloudformation
Provides-Extra: cloudformation_deprecated
Provides-Extra: cloudtrail
Provides-Extra: cloudwatch
Provides-Extra: cloudwatch_deprecated
Provides-Extra: codecommit
Provides-Extra: codepipeline
Provides-Extra: cognitoidentity
Provides-Extra: cognitoidentity_deprecated
Provides-Extra: cognitoidp
Provides-Extra: cognitoidp_deprecated
Provides-Extra: config
Provides-Extra: datapipeline
Provides-Extra: datapipeline_deprecated
Provides-Extra: datasync
Provides-Extra: dms
Provides-Extra: ds
Provides-Extra: dynamodb
Provides-Extra: dynamodb2
Provides-Extra: dynamodb2_deprecated
Provides-Extra: dynamodb_deprecated
Provides-Extra: dynamodbstreams
Provides-Extra: ec2
Provides-Extra: ec2_deprecated
Provides-Extra: ec2instanceconnect
Provides-Extra: ecr
Provides-Extra: ecr_deprecated
Provides-Extra: ecs
Provides-Extra: ecs_deprecated
Provides-Extra: efs
Provides-Extra: eks
Provides-Extra: elasticbeanstalk
Provides-Extra: elastictranscoder
Provides-Extra: elb
Provides-Extra: elb_deprecated
Provides-Extra: elbv2
Provides-Extra: emr
Provides-Extra: emr_deprecated
Provides-Extra: emrcontainers
Provides-Extra: events
Provides-Extra: firehose
Provides-Extra: forecast
Provides-Extra: glacier
Provides-Extra: glacier_deprecated
Provides-Extra: glue
Provides-Extra: iam
Provides-Extra: iam_deprecated
Provides-Extra: iot
Provides-Extra: iotdata
Provides-Extra: kinesis
Provides-Extra: kinesis_deprecated
Provides-Extra: kinesisvideo
Provides-Extra: kinesisvideoarchivedmedia
Provides-Extra: kms
Provides-Extra: kms_deprecated
Provides-Extra: lambda
Provides-Extra: lambda_deprecated
Provides-Extra: logs
Provides-Extra: logs_deprecated
Provides-Extra: managedblockchain
Provides-Extra: mediaconnect
Provides-Extra: medialive
Provides-Extra: mediapackage
Provides-Extra: mediastore
Provides-Extra: mediastoredata
Provides-Extra: opsworks
Provides-Extra: opsworks_deprecated
Provides-Extra: organizations
Provides-Extra: polly
Provides-Extra: ram
Provides-Extra: rds
Provides-Extra: rds2
Provides-Extra: rds2_deprecated
Provides-Extra: rds_deprecated
Provides-Extra: redshift
Provides-Extra: redshift_deprecated
Provides-Extra: resourcegroups
Provides-Extra: resourcegroupstaggingapi
Provides-Extra: route53
Provides-Extra: route53_deprecated
Provides-Extra: route53resolver
Provides-Extra: s3
Provides-Extra: s3_deprecated
Provides-Extra: sagemaker
Provides-Extra: sdb
Provides-Extra: secretsmanager
Provides-Extra: ses
Provides-Extra: ses_deprecated
Provides-Extra: sns
Provides-Extra: sns_deprecated
Provides-Extra: sqs
Provides-Extra: sqs_deprecated
Provides-Extra: ssm
Provides-Extra: stepfunctions
Provides-Extra: sts
Provides-Extra: sts_deprecated
Provides-Extra: support
Provides-Extra: swf
Provides-Extra: swf_deprecated
Provides-Extra: timestreamwrite
Provides-Extra: transcribe
Provides-Extra: wafv2
Provides-Extra: xray
Provides-Extra: xray_client
Provides-Extra: awslambda
License-File: LICENSE
License-File: AUTHORS.md
